{"mode":"plan","executed":false,"queryOnly":true,"evidenceSource":{"scope":"isolated-controlled","detection":"auto","dbPathClass":"temporary","realProfileRequired":false},"plan":{"status":"ready","sourceId":"file-provider","mode":"read-only","destructiveActions":false,"requiresApproval":true,"requiresSchemaChange":true,"requiresDataRewrite":true,"tableExists":true,"sourceScoped":false,"primaryKeyColumns":["path"],"existingRows":2,"rowsToMigrate":2,"blankPathRows":0,"invalidTimestampRows":0,"duplicatePathRows":0,"backupTableExists":false,"stagingTableExists":false,"blockers":[],"steps":["Create source-scoped staging table.","Backfill existing path-only rows into source_id=file-provider.","Rename path-only scan_progress to scan_progress_path_only_backup.","Rename staging table to scan_progress.","Create idx_scan_progress_path for path-based compatibility queries."],"rollback":"Keep scan_progress_path_only_backup until post-migration preflight, Settings diagnostics, and source-scoped read/write verification pass; rollback can rename the backup back to scan_progress or force provider-scoped full rescan.","verification":["Re-run search:index-migration:preflight and expect scanProgressSourceScope=ready.","Verify scan_progress has PRIMARY KEY(source_id, path).","Verify source-scoped read/delete/upsert only touches the intended sourceId.","Verify Settings diagnostics does not report cross-source progress contamination."]}}
