{"kind":"scan-progress-source-scope-simulation","generatedAt":"2026-06-24T19:22:40.802Z","mode":"copy-execute","destructiveActions":false,"sourceDb":"/tmp/tuff-r3-indexing-runtime-evidence-2026-06-25/profile-old-shape.sqlite","simulationDb":"/tmp/tuff-r3-indexing-runtime-evidence-2026-06-25/copies/scan-progress-simulation.sqlite","simulationDbKept":true,"sourceId":"file-provider","sourceBefore":{"tableExists":true,"sourceScoped":false,"primaryKeyColumns":["path"],"rowCount":2,"sourceRows":[],"backupTableExists":false,"backupRows":0},"sourceAfter":{"tableExists":true,"sourceScoped":false,"primaryKeyColumns":["path"],"rowCount":2,"sourceRows":[],"backupTableExists":false,"backupRows":0},"before":{"plan":{"status":"ready","sourceId":"file-provider","mode":"read-only","destructiveActions":false,"requiresApproval":true,"requiresSchemaChange":true,"requiresDataRewrite":true,"tableExists":true,"sourceScoped":false,"primaryKeyColumns":["path"],"existingRows":2,"rowsToMigrate":2,"blankPathRows":0,"invalidTimestampRows":0,"duplicatePathRows":0,"backupTableExists":false,"stagingTableExists":false,"blockers":[],"steps":["Create source-scoped staging table.","Backfill existing path-only rows into source_id=file-provider.","Rename path-only scan_progress to scan_progress_path_only_backup.","Rename staging table to scan_progress.","Create idx_scan_progress_path for path-based compatibility queries."],"rollback":"Keep scan_progress_path_only_backup until post-migration preflight, Settings diagnostics, and source-scoped read/write verification pass; rollback can rename the backup back to scan_progress or force provider-scoped full rescan.","verification":["Re-run search:index-migration:preflight and expect scanProgressSourceScope=ready.","Verify scan_progress has PRIMARY KEY(source_id, path).","Verify source-scoped read/delete/upsert only touches the intended sourceId.","Verify Settings diagnostics does not report cross-source progress contamination."]},"snapshot":{"tableExists":true,"sourceScoped":false,"primaryKeyColumns":["path"],"rowCount":2,"sourceRows":[],"backupTableExists":false,"backupRows":0}},"execution":{"executed":true,"migratedRows":2,"backupTable":"scan_progress_path_only_backup"},"after":{"plan":{"status":"not-needed","sourceId":"file-provider","mode":"read-only","destructiveActions":false,"requiresApproval":false,"requiresSchemaChange":false,"requiresDataRewrite":false,"tableExists":true,"sourceScoped":true,"primaryKeyColumns":["source_id","path"],"existingRows":2,"rowsToMigrate":0,"blankPathRows":0,"invalidTimestampRows":0,"duplicatePathRows":0,"backupTableExists":true,"stagingTableExists":false,"blockers":[],"steps":["scan_progress already has source_id and PRIMARY KEY(source_id, path)."],"rollback":"Keep scan_progress_path_only_backup until post-migration preflight, Settings diagnostics, and source-scoped read/write verification pass; rollback can rename the backup back to scan_progress or force provider-scoped full rescan.","verification":["Re-run search:index-migration:preflight and expect scanProgressSourceScope=ready.","Verify scan_progress has PRIMARY KEY(source_id, path).","Verify source-scoped read/delete/upsert only touches the intended sourceId.","Verify Settings diagnostics does not report cross-source progress contamination."]},"snapshot":{"tableExists":true,"sourceScoped":true,"primaryKeyColumns":["source_id","path"],"rowCount":2,"sourceRows":[{"sourceId":"file-provider","rows":2}],"backupTableExists":true,"backupRows":2}},"gate":{"passed":true,"blockers":[]},"verification":["Source --db was copied with VACUUM INTO and was not mutated.","Migration helper executed only against simulationDb.","Use search:index-migration:preflight on the original DB before any approved execute-mode migration.","Use search:scan-progress-migration --execute only after high-risk approval."]}
